bagua_quant-1.0.1.dist-info/METADATA
bagua_quant-1.0.1.dist-info/WHEEL
bagua_quant-1.0.1.dist-info/licenses/LICENSE
bagua/bagua.pyi
bagua/__init__.py
bagua/bagua.pypy310-pp73-ppc_64-linux-gnu.so
bagua_quant-1.0.1.dist-info/RECORD
